lisspyscope/__init__.py
lisspyscope/audio.py
lisspyscope/core.py
lisspyscope-0.1.2.dist-info/METADATA
lisspyscope-0.1.2.dist-info/WHEEL
lisspyscope-0.1.2.dist-info/entry_points.txt
lisspyscope-0.1.2.dist-info/licenses/LICENSE
lisspyscope-0.1.2.dist-info/RECORD
