Metadata-Version: 2.4
Name: lisspyscope
Version: 0.1.2
Summary: Generate, visualise and analyse Lissajous figures using python and oscilloscope.
Project-URL: Homepage, https://github.com/namanPuri/lisspyscope
Author-email: Naman Puri <namanpuri1712@gmail.com>
License: MIT
License-File: LICENSE
Requires-Python: >=3.8
Requires-Dist: numpy>=1.22
Requires-Dist: sounddevice>=0.4
Provides-Extra: plot
Requires-Dist: matplotlib>=3.7; extra == 'plot'
